thumbgen/__init__.py
thumbgen/thumbgen.py
thumbgen-0.1.1.dist-info/entry_points.txt
thumbgen-0.1.1.dist-info/LICENSE
thumbgen-0.1.1.dist-info/WHEEL
thumbgen-0.1.1.dist-info/METADATA
thumbgen-0.1.1.dist-info/RECORD
