Metadata-Version: 2.1
Name: thumbgen
Version: 0.1.1
Summary: Pre-generates thumbnails for 'Gnome Files' formerly known as nautilus.
Home-page: https://github.com/difference-engine/thumbnail-generator-ubuntu
License: MIT
Keywords: nautilus,thumbnail
Author: Mudassir Khan
Author-email: mudassirkhan19@gmail.com
Requires-Python: >=3.5,<4.0
Classifier: License :: OSI Approved :: MIT License
Classifier: Programming Language :: Python :: 3
Classifier: Programming Language :: Python :: 3.5
Classifier: Programming Language :: Python :: 3.6
Classifier: Programming Language :: Python :: 3.7
Requires-Dist: PyGObject (>=3.34,<4.0)
Requires-Dist: click (>=7.0,<8.0)
Requires-Dist: loguru (>=0.3.2,<0.4.0)
Requires-Dist: tqdm (>=4.36,<5.0)
Project-URL: Repository, https://github.com/difference-engine/thumbnail-generator-ubuntu
